gpu_wait/__init__.py
gpu_wait/cli.py
gpu_wait/command_runner.py
gpu_wait/gpu_monitor.py
gpu_wait-0.4.9.dist-info/METADATA
gpu_wait-0.4.9.dist-info/WHEEL
gpu_wait-0.4.9.dist-info/entry_points.txt
gpu_wait-0.4.9.dist-info/top_level.txt
gpu_wait-0.4.9.dist-info/RECORD
