Metadata-Version: 2.1
Name: gpu_wait
Version: 0.4.9
Summary: A package to run commands when GPU resources are available
Home-page: https://github.com/dipta007/gpu-wait
Author: Shubhashis Roy Dipta
Author-email: iamdipta@gmail.com
Classifier: Programming Language :: Python :: 3
Classifier: License :: OSI Approved :: MIT License
Classifier: Operating System :: OS Independent
Requires-Python: >=3.6
Requires-Dist: pynvml
Requires-Dist: psutil
Requires-Dist: click
